{"assets":{"4D228BDFA1F59F0125B92E3A19605505":{"type":"texture","index":1,"assetRequest":{"type":"slide","state":"contents","slide":"none"},"url":{"native":"assets/B4BC7CEF-A3D5-4588-A8AC-22A05CC9040B.pdf"},"width":1026,"height":13},"EF1056C4F088B7A9DBDF5AA7AB176A86":{"type":"texture","index":5,"assetRequest":{"type":"slide","state":"contents","slide":"none"},"url":{"native":"assets/B4BC7CEF-A3D5-4588-A8AC-22A05CC9040B.pdf"},"width":44,"height":36},"336208773D27FF0B1EEE8862274EFBD8":{"type":"texture","index":7,"assetRequest":{"type":"slide","state":"contents","slide":"none"},"url":{"native":"assets/B4BC7CEF-A3D5-4588-A8AC-22A05CC9040B.pdf"},"width":1024,"height":768},"D7D7E4D8DB5C357981D01D15B5C6A61B":{"type":"texture","index":2,"assetRequest":{"type":"slide","state":"contents","slide":"none"},"url":{"native":"assets/B4BC7CEF-A3D5-4588-A8AC-22A05CC9040B.pdf"},"width":300,"height":300},"0BD29801AF197E3A57AEDDF3FABD5E69":{"type":"texture","index":8,"assetRequest":{"type":"slide","state":"contents","slide":"none"},"url":{"native":"assets/B4BC7CEF-A3D5-4588-A8AC-22A05CC9040B.pdf"},"width":1024,"height":768},"57F37F491EDE3BFBC2330D8CB150D3FD":{"type":"texture","index":3,"assetRequest":{"type":"slide","state":"contents","slide":"none"},"url":{"native":"assets/B4BC7CEF-A3D5-4588-A8AC-22A05CC9040B.pdf"},"width":172,"height":300},"BB5FBA3B6F10FBEC956A14E318AB3F6E":{"type":"texture","index":6,"assetRequest":{"type":"slide","state":"contents","slide":"none"},"url":{"native":"assets/B4BC7CEF-A3D5-4588-A8AC-22A05CC9040B.pdf"},"width":103,"height":19},"DFDBC287DA3C930BF833C0D0D18B1670":{"type":"texture","index":0,"assetRequest":{"type":"slide","state":"contents","slide":"none"},"url":{"native":"assets/B4BC7CEF-A3D5-4588-A8AC-22A05CC9040B.pdf"},"width":1024,"height":768},"72A2651E9F667A812EBAE78CE475F002":{"type":"texture","index":4,"assetRequest":{"type":"slide","state":"contents","slide":"none"},"url":{"native":"assets/B4BC7CEF-A3D5-4588-A8AC-22A05CC9040B.pdf"},"width":300,"height":158}},"events":[{"effects":[{"beginTime":0,"baseLayer":{"animations":[],"initialState":{"affineTransform":[1,0,0,1,0,0],"masksToBounds":false,"rotation":0,"scale":1,"position":{"pointX":208,"pointY":384},"width":297.947265625,"sublayerTransform":[1,0,0,0,0,1,0,0,0,0,1,0,0,0,0,1],"contentsRect":{"y":0,"x":0,"width":1,"height":1},"opacity":1,"edgeAntialiasingMask":251658240,"height":297.947265625,"hidden":false,"anchorPoint":{"pointX":0.5,"pointY":0.5}},"objectID":"A8A4ABB2-10C0-44A2-8E79-2ED18D4FC8FC","layers":[{"animations":[],"initialState":{"affineTransform":[1,0,0,1,0,0],"masksToBounds":false,"rotation":0,"scale":1,"position":{"pointX":452.9736328125,"pointY":148.9736328125},"width":297.947265625,"sublayerTransform":[1,0,0,0,0,1,0,0,0,0,1,-0.0004922987690640373,0,0,0,1],"contentsRect":{"y":0,"x":0,"width":1,"height":1},"opacity":1,"edgeAntialiasingMask":251658240,"height":297.947265625,"hidden":false,"anchorPoint":{"pointX":1.520314784102157,"pointY":0.5}},"layers":[{"animations":[{"timeOffset":0,"beginTime":1e-100,"repeatCount":0,"animations":[{"timeOffset":0,"from":{"scalar":0},"beginTime":0,"repeatCount":0,"fillMode":"both","duration":1,"autoreverses":false,"timingFunction":"EaseInEaseOut","property":"opacity","to":{"scalar":1}},{"timeOffset":0,"from":{"scalar":false},"beginTime":0,"repeatCount":0,"fillMode":"forwards","property":"hidden","autoreverses":false,"duration":1,"to":{"scalar":false}}],"fillMode":"both","autoreverses":false,"duration":1}],"layers":[],"texturedRectangle":{"isBackgroundTexture":true,"singleTextureOpacity":1,"textureType":5,"textBaseline":0,"textXHeight":0,"isVerticalText":false},"initialState":{"affineTransform":[1,0,0,1,0,0],"masksToBounds":false,"rotation":0,"scale":1,"position":{"pointX":148.9736328125,"pointY":148.9736328125},"width":300,"sublayerTransform":[1,0,0,0,0,1,0,0,0,0,1,0,0,0,0,1],"contentsRect":{"y":0,"x":0,"width":1,"height":1},"opacity":1,"edgeAntialiasingMask":0,"height":300,"hidden":true,"anchorPoint":{"pointX":0.5,"pointY":0.5}},"texture":"D7D7E4D8DB5C357981D01D15B5C6A61B"}]}]},"effects":[],"duration":1,"type":"buildIn","name":"apple:dissolve","objectID":"A8A4ABB2-10C0-44A2-8E79-2ED18D4FC8FC"}],"automaticPlay":false,"hyperlinks":[],"accessibility":[{"text":"SERVIDOR","targetRectangle":{"y":729.2687065601349,"x":908.6099982261658,"width":100.78,"height":24.41986083984375}}],"baseLayer":{"animations":[],"initialState":{"affineTransform":[1,0,0,1,0,0],"masksToBounds":false,"rotation":0,"scale":1,"position":{"pointX":512,"pointY":384},"width":1024,"sublayerTransform":[1,0,0,0,0,1,0,0,0,0,1,0,0,0,0,1],"contentsRect":{"y":0,"x":0,"width":1,"height":1},"opacity":1,"edgeAntialiasingMask":251658240,"height":768,"hidden":false,"anchorPoint":{"pointX":0.5,"pointY":0.5}},"layers":[{"animations":[],"initialState":{"affineTransform":[1,0,0,1,0,0],"masksToBounds":false,"rotation":0,"scale":1,"position":{"pointX":512,"pointY":384},"width":1024,"sublayerTransform":[1,0,0,0,0,1,0,0,0,0,1,0,0,0,0,1],"contentsRect":{"y":0,"x":0,"width":1,"height":1},"opacity":1,"edgeAntialiasingMask":251658240,"height":768,"hidden":false,"anchorPoint":{"pointX":0.5,"pointY":0.5}},"layers":[{"animations":[],"initialState":{"affineTransform":[1,0,0,1,0,0],"masksToBounds":false,"rotation":0,"scale":1,"position":{"pointX":512,"pointY":384},"width":1024,"sublayerTransform":[1,0,0,0,0,1,0,0,0,0,1,0,0,0,0,1],"contentsRect":{"y":0,"x":0,"width":1,"height":1},"opacity":1,"edgeAntialiasingMask":251658240,"height":768,"hidden":false,"anchorPoint":{"pointX":0.5,"pointY":0.5}},"layers":[{"animations":[],"layers":[],"texturedRectangle":{"isBackgroundTexture":true,"singleTextureOpacity":1,"textureType":1,"textBaseline":0,"textXHeight":0,"isVerticalText":false},"initialState":{"affineTransform":[1,0,0,1,0,0],"masksToBounds":false,"rotation":0,"scale":1,"position":{"pointX":512,"pointY":384},"width":1024,"sublayerTransform":[1,0,0,0,0,1,0,0,0,0,1,0,0,0,0,1],"contentsRect":{"y":0,"x":0,"width":1,"height":1},"opacity":1,"edgeAntialiasingMask":0,"height":768,"hidden":false,"anchorPoint":{"pointX":0.5,"pointY":0.5}},"texture":"DFDBC287DA3C930BF833C0D0D18B1670"}]}]},{"animations":[],"initialState":{"affineTransform":[1,0,0,1,0,0],"masksToBounds":false,"rotation":0,"scale":1,"position":{"pointX":512,"pointY":384},"width":1024,"sublayerTransform":[1,0,0,0,0,1,0,0,0,0,1,0,0,0,0,1],"contentsRect":{"y":0,"x":0,"width":1,"height":1},"opacity":1,"edgeAntialiasingMask":251658240,"height":768,"hidden":false,"anchorPoint":{"pointX":0.5,"pointY":0.5}},"layers":[{"animations":[],"initialState":{"affineTransform":[1,0,0,1,0,0],"masksToBounds":false,"rotation":0,"scale":1,"position":{"pointX":512,"pointY":4.771605014801025},"width":1024,"sublayerTransform":[1,0,0,0,0,1,0,0,0,0,1,0,0,0,0,1],"contentsRect":{"y":0,"x":0,"width":1,"height":1},"opacity":1,"edgeAntialiasingMask":251658240,"height":9.9453125,"hidden":false,"anchorPoint":{"pointX":0.5,"pointY":0.5}},"layers":[{"animations":[],"layers":[],"texturedRectangle":{"singleTextureOpacity":1,"textXHeight":0,"shapePath":{"lineWidth":1,"flatness":0.6,"lineCapStyle":0,"elements":[{"type":"MoveToPoint","points":[[1,1.798948764801025]]},{"type":"AddLine","points":[[1025,1.798948764801025]]},{"type":"AddLine","points":[[1025,11.74426126480103]]},{"type":"AddLine","points":[[1,11.74426126480103]]},{"type":"CloseSubpath"},{"type":"MoveToPoint","points":[[1,1.798948764801025]]}],"windingRule":0,"lineJoinStyle":0,"miterLimit":10},"isBackgroundTexture":true,"textBaseline":0,"isVerticalText":false,"textureType":5},"initialState":{"affineTransform":[1,0,0,1,0,0],"masksToBounds":false,"rotation":0,"scale":1,"position":{"pointX":512,"pointY":4.701051235198975},"width":1026,"sublayerTransform":[1,0,0,0,0,1,0,0,0,0,1,0,0,0,0,1],"contentsRect":{"y":0,"x":0,"width":1,"height":1},"opacity":1,"edgeAntialiasingMask":0,"height":13,"hidden":false,"anchorPoint":{"pointX":0.5,"pointY":0.5}},"texture":"4D228BDFA1F59F0125B92E3A19605505"}]}]},{"animations":[],"initialState":{"affineTransform":[1,0,0,1,0,0],"masksToBounds":false,"rotation":0,"scale":1,"position":{"pointX":512,"pointY":384},"width":1024,"sublayerTransform":[1,0,0,0,0,1,0,0,0,0,1,0,0,0,0,1],"contentsRect":{"y":0,"x":0,"width":1,"height":1},"opacity":1,"edgeAntialiasingMask":251658240,"height":768,"hidden":false,"anchorPoint":{"pointX":0.5,"pointY":0.5}},"layers":[{"animations":[],"initialState":{"affineTransform":[1,0,0,1,0,0],"masksToBounds":false,"rotation":0,"scale":1,"position":{"pointX":208,"pointY":384},"width":297.947265625,"sublayerTransform":[1,0,0,0,0,1,0,0,0,0,1,0,0,0,0,1],"contentsRect":{"y":0,"x":0,"width":1,"height":1},"opacity":1,"edgeAntialiasingMask":251658240,"height":297.947265625,"hidden":false,"anchorPoint":{"pointX":0.5,"pointY":0.5}},"objectID":"A8A4ABB2-10C0-44A2-8E79-2ED18D4FC8FC","layers":[{"animations":[],"layers":[],"texturedRectangle":{"isBackgroundTexture":true,"singleTextureOpacity":1,"textureType":5,"textBaseline":0,"textXHeight":0,"isVerticalText":false},"initialState":{"affineTransform":[1,0,0,1,0,0],"masksToBounds":false,"rotation":0,"scale":1,"position":{"pointX":148.9736328125,"pointY":148.9736328125},"width":300,"sublayerTransform":[1,0,0,0,0,1,0,0,0,0,1,0,0,0,0,1],"contentsRect":{"y":0,"x":0,"width":1,"height":1},"opacity":1,"edgeAntialiasingMask":0,"height":300,"hidden":true,"anchorPoint":{"pointX":0.5,"pointY":0.5}},"texture":"D7D7E4D8DB5C357981D01D15B5C6A61B"}]}]},{"animations":[],"initialState":{"affineTransform":[1,0,0,1,0,0],"masksToBounds":false,"rotation":0,"scale":1,"position":{"pointX":512,"pointY":384},"width":1024,"sublayerTransform":[1,0,0,0,0,1,0,0,0,0,1,0,0,0,0,1],"contentsRect":{"y":0,"x":0,"width":1,"height":1},"opacity":1,"edgeAntialiasingMask":251658240,"height":768,"hidden":false,"anchorPoint":{"pointX":0.5,"pointY":0.5}},"layers":[{"animations":[],"initialState":{"affineTransform":[1,0,0,1,0,0],"masksToBounds":false,"rotation":0,"scale":1,"position":{"pointX":512.0000076293945,"pointY":384},"width":168.6371002197266,"sublayerTransform":[1,0,0,0,0,1,0,0,0,0,1,0,0,0,0,1],"contentsRect":{"y":0,"x":0,"width":1,"height":1},"opacity":1,"edgeAntialiasingMask":251658240,"height":297.947265625,"hidden":false,"anchorPoint":{"pointX":0.5,"pointY":0.5}},"objectID":"499115BB-BDA5-48F8-98AC-F013E4FB8150","layers":[{"animations":[],"layers":[],"texturedRectangle":{"isBackgroundTexture":true,"singleTextureOpacity":1,"textureType":5,"textBaseline":0,"textXHeight":0,"isVerticalText":false},"initialState":{"affineTransform":[1,0,0,1,0,0],"masksToBounds":false,"rotation":0,"scale":1,"position":{"pointX":84.31854248046875,"pointY":148.9736328125},"width":172,"sublayerTransform":[1,0,0,0,0,1,0,0,0,0,1,0,0,0,0,1],"contentsRect":{"y":0,"x":0,"width":1,"height":1},"opacity":1,"edgeAntialiasingMask":0,"height":300,"hidden":true,"anchorPoint":{"pointX":0.5,"pointY":0.5}},"texture":"57F37F491EDE3BFBC2330D8CB150D3FD"}]}]},{"animations":[],"initialState":{"affineTransform":[1,0,0,1,0,0],"masksToBounds":false,"rotation":0,"scale":1,"position":{"pointX":512,"pointY":384},"width":1024,"sublayerTransform":[1,0,0,0,0,1,0,0,0,0,1,0,0,0,0,1],"contentsRect":{"y":0,"x":0,"width":1,"height":1},"opacity":1,"edgeAntialiasingMask":251658240,"height":768,"hidden":false,"anchorPoint":{"pointX":0.5,"pointY":0.5}},"layers":[{"animations":[],"initialState":{"affineTransform":[1,0,0,1,0,0],"masksToBounds":false,"rotation":0,"scale":1,"position":{"pointX":797,"pointY":384.0000152587891},"width":297.947265625,"sublayerTransform":[1,0,0,0,0,1,0,0,0,0,1,0,0,0,0,1],"contentsRect":{"y":0,"x":0,"width":1,"height":1},"opacity":1,"edgeAntialiasingMask":251658240,"height":154.1877136230469,"hidden":false,"anchorPoint":{"pointX":0.5,"pointY":0.5}},"objectID":"5F068AF4-49C1-41BD-9D0B-F351C387611E","layers":[{"animations":[],"layers":[],"texturedRectangle":{"isBackgroundTexture":true,"singleTextureOpacity":1,"textureType":5,"textBaseline":0,"textXHeight":0,"isVerticalText":false},"initialState":{"affineTransform":[1,0,0,1,0,0],"masksToBounds":false,"rotation":0,"scale":1,"position":{"pointX":148.9736328125,"pointY":77.09384155273438},"width":300,"sublayerTransform":[1,0,0,0,0,1,0,0,0,0,1,0,0,0,0,1],"contentsRect":{"y":0,"x":0,"width":1,"height":1},"opacity":1,"edgeAntialiasingMask":0,"height":158,"hidden":true,"anchorPoint":{"pointX":0.5,"pointY":0.5}},"texture":"72A2651E9F667A812EBAE78CE475F002"}]}]},{"animations":[],"initialState":{"affineTransform":[1,0,0,1,0,0],"masksToBounds":false,"rotation":0,"scale":1,"position":{"pointX":512,"pointY":384},"width":1024,"sublayerTransform":[1,0,0,0,0,1,0,0,0,0,1,0,0,0,0,1],"contentsRect":{"y":0,"x":0,"width":1,"height":1},"opacity":1,"edgeAntialiasingMask":251658240,"height":768,"hidden":false,"anchorPoint":{"pointX":0.5,"pointY":0.5}},"layers":[{"animations":[],"initialState":{"affineTransform":[1,0,0,1,0,0],"masksToBounds":false,"rotation":0,"scale":1,"position":{"pointX":874.1346811056137,"pointY":741.4786378622521},"width":40.90644717216492,"sublayerTransform":[1,0,0,0,0,1,0,0,0,0,1,0,0,0,0,1],"contentsRect":{"y":0,"x":0,"width":1,"height":1},"opacity":1,"edgeAntialiasingMask":251658240,"height":33.00000033387914,"hidden":false,"anchorPoint":{"pointX":0.5,"pointY":0.5}},"layers":[{"animations":[],"layers":[],"texturedRectangle":{"singleTextureOpacity":1,"textXHeight":0,"shapePath":{"lineWidth":1,"flatness":0.6,"lineCapStyle":0,"elements":[{"type":"MoveToPoint","points":[[2.563502786681056,1.9786376953125]]},{"type":"AddCurve","points":[[2.077943146394546,1.9786376953125],[1.681459079988372,2.375123351061688],[1.68145751953125,2.860683026723564]]},{"type":"AddLine","points":[[1.68145751953125,29.14307724963874]]},{"type":"AddCurve","points":[[1.68145751953125,29.62863536484338],[2.077946267308789,30.02512882287874],[2.563502786681056,30.0251225810498]]},{"type":"AddLine","points":[[18.58732513990253,30.0251225810498]]},{"type":"AddLine","points":[[18.52980044856668,30.27120044524781]]},{"type":"AddLine","points":[[17.84269996872172,33.70350727834739]]},{"type":"AddLine","points":[[15.83253158815205,33.70350727834739]]},{"type":"AddLine","points":[[15.83253158815205,34.97863802919164]]},{"type":"AddLine","points":[[21.12799900723621,34.97863802919164]]},{"type":"AddLine","points":[[22.30725517962128,34.97863802919164]]},{"type":"AddLine","points":[[27.60272259870544,34.97863802919164]]},{"type":"AddLine","points":[[27.60272259870544,33.70350727834739]]},{"type":"AddLine","points":[[25.59255421813577,33.70350727834739]]},{"type":"AddLine","points":[[24.90545373829082,30.27120044524781]]},{"type":"AddLine","points":[[24.85112486314029,30.0251225810498]]},{"type":"AddLine","points":[[41.70585942454636,30.0251225810498]]},{"type":"AddCurve","points":[[42.19141750437575,30.0251225810498],[42.58790469169617,29.62863224392891],[42.58790469169617,29.14307724963874]]},{"type":"AddLine","points":[[42.58790469169617,2.860683026723564]]},{"type":"AddCurve","points":[[42.5876987113561,2.375123351061688],[42.19142374620424,1.9786376953125],[41.70585942454636,1.9786376953125]]},{"type":"AddLine","points":[[2.563502786681056,1.9786376953125]]},{"type":"CloseSubpath"},{"type":"MoveToPoint","points":[[22.13468110561371,2.793570881942287]]},{"type":"AddCurve","points":[[22.35138178610987,2.793570881942287],[22.52776649640873,2.969957165548863],[22.52776649640873,3.186656301375479]]},{"type":"AddCurve","points":[[22.52776649640873,3.403358558116565],[22.35137554428138,3.576542783476043],[22.13468110561371,3.576545904390514]]},{"type":"AddCurve","points":[[21.91798042511755,3.576545904390514],[21.74159571481869,3.403360118573801],[21.74159571481869,3.186656301375479]]},{"type":"AddCurve","points":[[21.74159571481869,2.969954044634392],[21.91798666694604,2.793569321485052],[22.13468110561371,2.793570881942287]]},{"type":"CloseSubpath"},{"type":"MoveToPoint","points":[[4.033578231930733,4.624773689545691]]},{"type":"AddLine","points":[[40.23578397929668,4.624773689545691]]},{"type":"AddLine","points":[[40.23578397929668,25.24418121948838]]},{"type":"AddLine","points":[[4.033578231930733,25.24418121948838]]},{"type":"AddLine","points":[[4.033578231930733,4.624773689545691]]},{"type":"CloseSubpath"},{"type":"MoveToPoint","points":[[4.033578231930733,4.624773689545691]]}],"windingRule":0,"lineJoinStyle":0,"miterLimit":10},"isBackgroundTexture":true,"textBaseline":0,"isVerticalText":false,"textureType":5},"initialState":{"affineTransform":[1,0,0,1,0,0],"masksToBounds":false,"rotation":0,"scale":1,"position":{"pointX":20.31854248046875,"pointY":16.0213623046875},"width":44,"sublayerTransform":[1,0,0,0,0,1,0,0,0,0,1,0,0,0,0,1],"contentsRect":{"y":0,"x":0,"width":1,"height":1},"opacity":1,"edgeAntialiasingMask":0,"height":36,"hidden":false,"anchorPoint":{"pointX":0.5,"pointY":0.5}},"texture":"EF1056C4F088B7A9DBDF5AA7AB176A86"}]}]},{"animations":[],"initialState":{"affineTransform":[1,0,0,1,0,0],"masksToBounds":false,"rotation":0,"scale":1,"position":{"pointX":512,"pointY":384},"width":1024,"sublayerTransform":[1,0,0,0,0,1,0,0,0,0,1,0,0,0,0,1],"contentsRect":{"y":0,"x":0,"width":1,"height":1},"opacity":1,"edgeAntialiasingMask":251658240,"height":768,"hidden":false,"anchorPoint":{"pointX":0.5,"pointY":0.5}},"layers":[{"animations":[],"initialState":{"affineTransform":[1,0,0,1,0,0],"masksToBounds":false,"rotation":0,"scale":1,"position":{"pointX":959,"pointY":741.4786376953125},"width":107.7800035476685,"sublayerTransform":[1,0,0,0,0,1,0,0,0,0,1,0,0,0,0,1],"contentsRect":{"y":0,"x":0,"width":1,"height":1},"opacity":1,"edgeAntialiasingMask":251658240,"height":30.41986227035522,"hidden":false,"anchorPoint":{"pointX":0.5,"pointY":0.5}},"layers":[{"animations":[],"layers":[],"texturedRectangle":{"singleTextureOpacity":1,"textXHeight":0.5442105263157895,"textBaseline":0.8604559270959151,"isBackgroundTexture":true,"isVerticalText":false,"textColor":[0,0,0,0.5],"textureType":6},"initialState":{"affineTransform":[1,0,0,1,0,0],"masksToBounds":false,"rotation":0,"scale":1,"position":{"pointX":54.39000177383423,"pointY":16.23129343986511},"width":103,"sublayerTransform":[1,0,0,0,0,1,0,0,0,0,1,0,0,0,0,1],"contentsRect":{"y":0,"x":0,"width":1,"height":1},"opacity":1,"edgeAntialiasingMask":0,"height":19,"hidden":false,"anchorPoint":{"pointX":0.5,"pointY":0.5}},"texture":"BB5FBA3B6F10FBEC956A14E318AB3F6E"}]}]}]}},{"effects":[{"beginTime":0,"baseLayer":{"animations":[],"initialState":{"affineTransform":[1,0,0,1,0,0],"masksToBounds":false,"rotation":0,"scale":1,"position":{"pointX":512.0000076293945,"pointY":384},"width":168.6371002197266,"sublayerTransform":[1,0,0,0,0,1,0,0,0,0,1,0,0,0,0,1],"contentsRect":{"y":0,"x":0,"width":1,"height":1},"opacity":1,"edgeAntialiasingMask":251658240,"height":297.947265625,"hidden":false,"anchorPoint":{"pointX":0.5,"pointY":0.5}},"objectID":"499115BB-BDA5-48F8-98AC-F013E4FB8150","layers":[{"animations":[],"initialState":{"affineTransform":[1,0,0,1,0,0],"masksToBounds":false,"rotation":0,"scale":1,"position":{"pointX":84.31854248046875,"pointY":148.9736328125},"width":168.6371002197266,"sublayerTransform":[1,0,0,0,0,1,0,0,0,0,1,-0.0004922987690640373,0,0,0,1],"contentsRect":{"y":0,"x":0,"width":1,"height":1},"opacity":1,"edgeAntialiasingMask":251658240,"height":297.947265625,"hidden":false,"anchorPoint":{"pointX":0.4999999547585049,"pointY":0.5}},"layers":[{"animations":[{"timeOffset":0,"beginTime":1e-100,"repeatCount":0,"animations":[{"timeOffset":0,"from":{"scalar":0},"beginTime":0,"repeatCount":0,"fillMode":"both","duration":1,"autoreverses":false,"timingFunction":"EaseInEaseOut","property":"opacity","to":{"scalar":1}},{"timeOffset":0,"from":{"scalar":false},"beginTime":0,"repeatCount":0,"fillMode":"forwards","property":"hidden","autoreverses":false,"duration":1,"to":{"scalar":false}}],"fillMode":"both","autoreverses":false,"duration":1}],"layers":[],"texturedRectangle":{"isBackgroundTexture":true,"singleTextureOpacity":1,"textureType":5,"textBaseline":0,"textXHeight":0,"isVerticalText":false},"initialState":{"affineTransform":[1,0,0,1,0,0],"masksToBounds":false,"rotation":0,"scale":1,"position":{"pointX":84.31854248046875,"pointY":148.9736328125},"width":172,"sublayerTransform":[1,0,0,0,0,1,0,0,0,0,1,0,0,0,0,1],"contentsRect":{"y":0,"x":0,"width":1,"height":1},"opacity":1,"edgeAntialiasingMask":0,"height":300,"hidden":true,"anchorPoint":{"pointX":0.5,"pointY":0.5}},"texture":"57F37F491EDE3BFBC2330D8CB150D3FD"}]}]},"effects":[],"duration":1,"type":"buildIn","name":"apple:dissolve","objectID":"499115BB-BDA5-48F8-98AC-F013E4FB8150"}],"automaticPlay":false,"hyperlinks":[],"accessibility":[{"text":"SERVIDOR","targetRectangle":{"y":729.2687065601349,"x":908.6099982261658,"width":100.78,"height":24.41986083984375}},{"text":"2000px-Ardebian_logo.svg.png","targetRectangle":{"y":235.0263671875,"x":59.0263671875,"width":297.947265625,"height":297.947265625}}],"baseLayer":{"animations":[],"initialState":{"affineTransform":[1,0,0,1,0,0],"masksToBounds":false,"rotation":0,"scale":1,"position":{"pointX":512,"pointY":384},"width":1024,"sublayerTransform":[1,0,0,0,0,1,0,0,0,0,1,0,0,0,0,1],"contentsRect":{"y":0,"x":0,"width":1,"height":1},"opacity":1,"edgeAntialiasingMask":251658240,"height":768,"hidden":false,"anchorPoint":{"pointX":0.5,"pointY":0.5}},"layers":[{"animations":[],"initialState":{"affineTransform":[1,0,0,1,0,0],"masksToBounds":false,"rotation":0,"scale":1,"position":{"pointX":512,"pointY":384},"width":1024,"sublayerTransform":[1,0,0,0,0,1,0,0,0,0,1,0,0,0,0,1],"contentsRect":{"y":0,"x":0,"width":1,"height":1},"opacity":1,"edgeAntialiasingMask":251658240,"height":768,"hidden":false,"anchorPoint":{"pointX":0.5,"pointY":0.5}},"layers":[{"animations":[],"initialState":{"affineTransform":[1,0,0,1,0,0],"masksToBounds":false,"rotation":0,"scale":1,"position":{"pointX":512,"pointY":384},"width":1024,"sublayerTransform":[1,0,0,0,0,1,0,0,0,0,1,0,0,0,0,1],"contentsRect":{"y":0,"x":0,"width":1,"height":1},"opacity":1,"edgeAntialiasingMask":251658240,"height":768,"hidden":false,"anchorPoint":{"pointX":0.5,"pointY":0.5}},"layers":[{"animations":[],"layers":[],"texturedRectangle":{"isBackgroundTexture":true,"singleTextureOpacity":1,"textureType":1,"textBaseline":0,"textXHeight":0,"isVerticalText":false},"initialState":{"affineTransform":[1,0,0,1,0,0],"masksToBounds":false,"rotation":0,"scale":1,"position":{"pointX":512,"pointY":384},"width":1024,"sublayerTransform":[1,0,0,0,0,1,0,0,0,0,1,0,0,0,0,1],"contentsRect":{"y":0,"x":0,"width":1,"height":1},"opacity":1,"edgeAntialiasingMask":0,"height":768,"hidden":false,"anchorPoint":{"pointX":0.5,"pointY":0.5}},"texture":"DFDBC287DA3C930BF833C0D0D18B1670"}]}]},{"animations":[],"initialState":{"affineTransform":[1,0,0,1,0,0],"masksToBounds":false,"rotation":0,"scale":1,"position":{"pointX":512,"pointY":384},"width":1024,"sublayerTransform":[1,0,0,0,0,1,0,0,0,0,1,0,0,0,0,1],"contentsRect":{"y":0,"x":0,"width":1,"height":1},"opacity":1,"edgeAntialiasingMask":251658240,"height":768,"hidden":false,"anchorPoint":{"pointX":0.5,"pointY":0.5}},"layers":[{"animations":[],"initialState":{"affineTransform":[1,0,0,1,0,0],"masksToBounds":false,"rotation":0,"scale":1,"position":{"pointX":512,"pointY":4.771605014801025},"width":1024,"sublayerTransform":[1,0,0,0,0,1,0,0,0,0,1,0,0,0,0,1],"contentsRect":{"y":0,"x":0,"width":1,"height":1},"opacity":1,"edgeAntialiasingMask":251658240,"height":9.9453125,"hidden":false,"anchorPoint":{"pointX":0.5,"pointY":0.5}},"layers":[{"animations":[],"layers":[],"texturedRectangle":{"singleTextureOpacity":1,"textXHeight":0,"shapePath":{"lineWidth":1,"flatness":0.6,"lineCapStyle":0,"elements":[{"type":"MoveToPoint","points":[[1,1.798948764801025]]},{"type":"AddLine","points":[[1025,1.798948764801025]]},{"type":"AddLine","points":[[1025,11.74426126480103]]},{"type":"AddLine","points":[[1,11.74426126480103]]},{"type":"CloseSubpath"},{"type":"MoveToPoint","points":[[1,1.798948764801025]]}],"windingRule":0,"lineJoinStyle":0,"miterLimit":10},"isBackgroundTexture":true,"textBaseline":0,"isVerticalText":false,"textureType":5},"initialState":{"affineTransform":[1,0,0,1,0,0],"masksToBounds":false,"rotation":0,"scale":1,"position":{"pointX":512,"pointY":4.701051235198975},"width":1026,"sublayerTransform":[1,0,0,0,0,1,0,0,0,0,1,0,0,0,0,1],"contentsRect":{"y":0,"x":0,"width":1,"height":1},"opacity":1,"edgeAntialiasingMask":0,"height":13,"hidden":false,"anchorPoint":{"pointX":0.5,"pointY":0.5}},"texture":"4D228BDFA1F59F0125B92E3A19605505"}]}]},{"animations":[],"initialState":{"affineTransform":[1,0,0,1,0,0],"masksToBounds":false,"rotation":0,"scale":1,"position":{"pointX":512,"pointY":384},"width":1024,"sublayerTransform":[1,0,0,0,0,1,0,0,0,0,1,0,0,0,0,1],"contentsRect":{"y":0,"x":0,"width":1,"height":1},"opacity":1,"edgeAntialiasingMask":251658240,"height":768,"hidden":false,"anchorPoint":{"pointX":0.5,"pointY":0.5}},"layers":[{"animations":[],"initialState":{"affineTransform":[1,0,0,1,0,0],"masksToBounds":false,"rotation":0,"scale":1,"position":{"pointX":208,"pointY":384},"width":297.947265625,"sublayerTransform":[1,0,0,0,0,1,0,0,0,0,1,0,0,0,0,1],"contentsRect":{"y":0,"x":0,"width":1,"height":1},"opacity":1,"edgeAntialiasingMask":251658240,"height":297.947265625,"hidden":false,"anchorPoint":{"pointX":0.5,"pointY":0.5}},"objectID":"A8A4ABB2-10C0-44A2-8E79-2ED18D4FC8FC","layers":[{"animations":[],"layers":[],"texturedRectangle":{"isBackgroundTexture":true,"singleTextureOpacity":1,"textureType":5,"textBaseline":0,"textXHeight":0,"isVerticalText":false},"initialState":{"affineTransform":[1,0,0,1,0,0],"masksToBounds":false,"rotation":0,"scale":1,"position":{"pointX":148.9736328125,"pointY":148.9736328125},"width":300,"sublayerTransform":[1,0,0,0,0,1,0,0,0,0,1,0,0,0,0,1],"contentsRect":{"y":0,"x":0,"width":1,"height":1},"opacity":1,"edgeAntialiasingMask":0,"height":300,"hidden":false,"anchorPoint":{"pointX":0.5,"pointY":0.5}},"texture":"D7D7E4D8DB5C357981D01D15B5C6A61B"}]}]},{"animations":[],"initialState":{"affineTransform":[1,0,0,1,0,0],"masksToBounds":false,"rotation":0,"scale":1,"position":{"pointX":512,"pointY":384},"width":1024,"sublayerTransform":[1,0,0,0,0,1,0,0,0,0,1,0,0,0,0,1],"contentsRect":{"y":0,"x":0,"width":1,"height":1},"opacity":1,"edgeAntialiasingMask":251658240,"height":768,"hidden":false,"anchorPoint":{"pointX":0.5,"pointY":0.5}},"layers":[{"animations":[],"initialState":{"affineTransform":[1,0,0,1,0,0],"masksToBounds":false,"rotation":0,"scale":1,"position":{"pointX":512.0000076293945,"pointY":384},"width":168.6371002197266,"sublayerTransform":[1,0,0,0,0,1,0,0,0,0,1,0,0,0,0,1],"contentsRect":{"y":0,"x":0,"width":1,"height":1},"opacity":1,"edgeAntialiasingMask":251658240,"height":297.947265625,"hidden":false,"anchorPoint":{"pointX":0.5,"pointY":0.5}},"objectID":"499115BB-BDA5-48F8-98AC-F013E4FB8150","layers":[{"animations":[],"layers":[],"texturedRectangle":{"isBackgroundTexture":true,"singleTextureOpacity":1,"textureType":5,"textBaseline":0,"textXHeight":0,"isVerticalText":false},"initialState":{"affineTransform":[1,0,0,1,0,0],"masksToBounds":false,"rotation":0,"scale":1,"position":{"pointX":84.31854248046875,"pointY":148.9736328125},"width":172,"sublayerTransform":[1,0,0,0,0,1,0,0,0,0,1,0,0,0,0,1],"contentsRect":{"y":0,"x":0,"width":1,"height":1},"opacity":1,"edgeAntialiasingMask":0,"height":300,"hidden":true,"anchorPoint":{"pointX":0.5,"pointY":0.5}},"texture":"57F37F491EDE3BFBC2330D8CB150D3FD"}]}]},{"animations":[],"initialState":{"affineTransform":[1,0,0,1,0,0],"masksToBounds":false,"rotation":0,"scale":1,"position":{"pointX":512,"pointY":384},"width":1024,"sublayerTransform":[1,0,0,0,0,1,0,0,0,0,1,0,0,0,0,1],"contentsRect":{"y":0,"x":0,"width":1,"height":1},"opacity":1,"edgeAntialiasingMask":251658240,"height":768,"hidden":false,"anchorPoint":{"pointX":0.5,"pointY":0.5}},"layers":[{"animations":[],"initialState":{"affineTransform":[1,0,0,1,0,0],"masksToBounds":false,"rotation":0,"scale":1,"position":{"pointX":797,"pointY":384.0000152587891},"width":297.947265625,"sublayerTransform":[1,0,0,0,0,1,0,0,0,0,1,0,0,0,0,1],"contentsRect":{"y":0,"x":0,"width":1,"height":1},"opacity":1,"edgeAntialiasingMask":251658240,"height":154.1877136230469,"hidden":false,"anchorPoint":{"pointX":0.5,"pointY":0.5}},"objectID":"5F068AF4-49C1-41BD-9D0B-F351C387611E","layers":[{"animations":[],"layers":[],"texturedRectangle":{"isBackgroundTexture":true,"singleTextureOpacity":1,"textureType":5,"textBaseline":0,"textXHeight":0,"isVerticalText":false},"initialState":{"affineTransform":[1,0,0,1,0,0],"masksToBounds":false,"rotation":0,"scale":1,"position":{"pointX":148.9736328125,"pointY":77.09384155273438},"width":300,"sublayerTransform":[1,0,0,0,0,1,0,0,0,0,1,0,0,0,0,1],"contentsRect":{"y":0,"x":0,"width":1,"height":1},"opacity":1,"edgeAntialiasingMask":0,"height":158,"hidden":true,"anchorPoint":{"pointX":0.5,"pointY":0.5}},"texture":"72A2651E9F667A812EBAE78CE475F002"}]}]},{"animations":[],"initialState":{"affineTransform":[1,0,0,1,0,0],"masksToBounds":false,"rotation":0,"scale":1,"position":{"pointX":512,"pointY":384},"width":1024,"sublayerTransform":[1,0,0,0,0,1,0,0,0,0,1,0,0,0,0,1],"contentsRect":{"y":0,"x":0,"width":1,"height":1},"opacity":1,"edgeAntialiasingMask":251658240,"height":768,"hidden":false,"anchorPoint":{"pointX":0.5,"pointY":0.5}},"layers":[{"animations":[],"initialState":{"affineTransform":[1,0,0,1,0,0],"masksToBounds":false,"rotation":0,"scale":1,"position":{"pointX":874.1346811056137,"pointY":741.4786378622521},"width":40.90644717216492,"sublayerTransform":[1,0,0,0,0,1,0,0,0,0,1,0,0,0,0,1],"contentsRect":{"y":0,"x":0,"width":1,"height":1},"opacity":1,"edgeAntialiasingMask":251658240,"height":33.00000033387914,"hidden":false,"anchorPoint":{"pointX":0.5,"pointY":0.5}},"layers":[{"animations":[],"layers":[],"texturedRectangle":{"singleTextureOpacity":1,"textXHeight":0,"shapePath":{"lineWidth":1,"flatness":0.6,"lineCapStyle":0,"elements":[{"type":"MoveToPoint","points":[[2.563502786681056,1.9786376953125]]},{"type":"AddCurve","points":[[2.077943146394546,1.9786376953125],[1.681459079988372,2.375123351061688],[1.68145751953125,2.860683026723564]]},{"type":"AddLine","points":[[1.68145751953125,29.14307724963874]]},{"type":"AddCurve","points":[[1.68145751953125,29.62863536484338],[2.077946267308789,30.02512882287874],[2.563502786681056,30.0251225810498]]},{"type":"AddLine","points":[[18.58732513990253,30.0251225810498]]},{"type":"AddLine","points":[[18.52980044856668,30.27120044524781]]},{"type":"AddLine","points":[[17.84269996872172,33.70350727834739]]},{"type":"AddLine","points":[[15.83253158815205,33.70350727834739]]},{"type":"AddLine","points":[[15.83253158815205,34.97863802919164]]},{"type":"AddLine","points":[[21.12799900723621,34.97863802919164]]},{"type":"AddLine","points":[[22.30725517962128,34.97863802919164]]},{"type":"AddLine","points":[[27.60272259870544,34.97863802919164]]},{"type":"AddLine","points":[[27.60272259870544,33.70350727834739]]},{"type":"AddLine","points":[[25.59255421813577,33.70350727834739]]},{"type":"AddLine","points":[[24.90545373829082,30.27120044524781]]},{"type":"AddLine","points":[[24.85112486314029,30.0251225810498]]},{"type":"AddLine","points":[[41.70585942454636,30.0251225810498]]},{"type":"AddCurve","points":[[42.19141750437575,30.0251225810498],[42.58790469169617,29.62863224392891],[42.58790469169617,29.14307724963874]]},{"type":"AddLine","points":[[42.58790469169617,2.860683026723564]]},{"type":"AddCurve","points":[[42.5876987113561,2.375123351061688],[42.19142374620424,1.9786376953125],[41.70585942454636,1.9786376953125]]},{"type":"AddLine","points":[[2.563502786681056,1.9786376953125]]},{"type":"CloseSubpath"},{"type":"MoveToPoint","points":[[22.13468110561371,2.793570881942287]]},{"type":"AddCurve","points":[[22.35138178610987,2.793570881942287],[22.52776649640873,2.969957165548863],[22.52776649640873,3.186656301375479]]},{"type":"AddCurve","points":[[22.52776649640873,3.403358558116565],[22.35137554428138,3.576542783476043],[22.13468110561371,3.576545904390514]]},{"type":"AddCurve","points":[[21.91798042511755,3.576545904390514],[21.74159571481869,3.403360118573801],[21.74159571481869,3.186656301375479]]},{"type":"AddCurve","points":[[21.74159571481869,2.969954044634392],[21.91798666694604,2.793569321485052],[22.13468110561371,2.793570881942287]]},{"type":"CloseSubpath"},{"type":"MoveToPoint","points":[[4.033578231930733,4.624773689545691]]},{"type":"AddLine","points":[[40.23578397929668,4.624773689545691]]},{"type":"AddLine","points":[[40.23578397929668,25.24418121948838]]},{"type":"AddLine","points":[[4.033578231930733,25.24418121948838]]},{"type":"AddLine","points":[[4.033578231930733,4.624773689545691]]},{"type":"CloseSubpath"},{"type":"MoveToPoint","points":[[4.033578231930733,4.624773689545691]]}],"windingRule":0,"lineJoinStyle":0,"miterLimit":10},"isBackgroundTexture":true,"textBaseline":0,"isVerticalText":false,"textureType":5},"initialState":{"affineTransform":[1,0,0,1,0,0],"masksToBounds":false,"rotation":0,"scale":1,"position":{"pointX":20.31854248046875,"pointY":16.0213623046875},"width":44,"sublayerTransform":[1,0,0,0,0,1,0,0,0,0,1,0,0,0,0,1],"contentsRect":{"y":0,"x":0,"width":1,"height":1},"opacity":1,"edgeAntialiasingMask":0,"height":36,"hidden":false,"anchorPoint":{"pointX":0.5,"pointY":0.5}},"texture":"EF1056C4F088B7A9DBDF5AA7AB176A86"}]}]},{"animations":[],"initialState":{"affineTransform":[1,0,0,1,0,0],"masksToBounds":false,"rotation":0,"scale":1,"position":{"pointX":512,"pointY":384},"width":1024,"sublayerTransform":[1,0,0,0,0,1,0,0,0,0,1,0,0,0,0,1],"contentsRect":{"y":0,"x":0,"width":1,"height":1},"opacity":1,"edgeAntialiasingMask":251658240,"height":768,"hidden":false,"anchorPoint":{"pointX":0.5,"pointY":0.5}},"layers":[{"animations":[],"initialState":{"affineTransform":[1,0,0,1,0,0],"masksToBounds":false,"rotation":0,"scale":1,"position":{"pointX":959,"pointY":741.4786376953125},"width":107.7800035476685,"sublayerTransform":[1,0,0,0,0,1,0,0,0,0,1,0,0,0,0,1],"contentsRect":{"y":0,"x":0,"width":1,"height":1},"opacity":1,"edgeAntialiasingMask":251658240,"height":30.41986227035522,"hidden":false,"anchorPoint":{"pointX":0.5,"pointY":0.5}},"layers":[{"animations":[],"layers":[],"texturedRectangle":{"singleTextureOpacity":1,"textXHeight":0.5442105263157895,"textBaseline":0.8604559270959151,"isBackgroundTexture":true,"isVerticalText":false,"textColor":[0,0,0,0.5],"textureType":6},"initialState":{"affineTransform":[1,0,0,1,0,0],"masksToBounds":false,"rotation":0,"scale":1,"position":{"pointX":54.39000177383423,"pointY":16.23129343986511},"width":103,"sublayerTransform":[1,0,0,0,0,1,0,0,0,0,1,0,0,0,0,1],"contentsRect":{"y":0,"x":0,"width":1,"height":1},"opacity":1,"edgeAntialiasingMask":0,"height":19,"hidden":false,"anchorPoint":{"pointX":0.5,"pointY":0.5}},"texture":"BB5FBA3B6F10FBEC956A14E318AB3F6E"}]}]}]}},{"effects":[{"beginTime":0,"baseLayer":{"animations":[],"initialState":{"affineTransform":[1,0,0,1,0,0],"masksToBounds":false,"rotation":0,"scale":1,"position":{"pointX":797,"pointY":384.0000152587891},"width":297.947265625,"sublayerTransform":[1,0,0,0,0,1,0,0,0,0,1,0,0,0,0,1],"contentsRect":{"y":0,"x":0,"width":1,"height":1},"opacity":1,"edgeAntialiasingMask":251658240,"height":154.1877136230469,"hidden":false,"anchorPoint":{"pointX":0.5,"pointY":0.5}},"objectID":"5F068AF4-49C1-41BD-9D0B-F351C387611E","layers":[{"animations":[],"initialState":{"affineTransform":[1,0,0,1,0,0],"masksToBounds":false,"rotation":0,"scale":1,"position":{"pointX":-136.0263671875,"pointY":77.09384155273438},"width":297.947265625,"sublayerTransform":[1,0,0,0,0,1,0,0,0,0,1,-0.0004922987690640373,0,0,0,1],"contentsRect":{"y":0,"x":0,"width":1,"height":1},"opacity":1,"edgeAntialiasingMask":251658240,"height":154.1877136230469,"hidden":false,"anchorPoint":{"pointX":-0.4565451100957725,"pointY":0.4999999010375814}},"layers":[{"animations":[{"timeOffset":0,"beginTime":1e-100,"repeatCount":0,"animations":[{"timeOffset":0,"from":{"scalar":0},"beginTime":0,"repeatCount":0,"fillMode":"both","duration":1,"autoreverses":false,"timingFunction":"EaseInEaseOut","property":"opacity","to":{"scalar":1}},{"timeOffset":0,"from":{"scalar":false},"beginTime":0,"repeatCount":0,"fillMode":"forwards","property":"hidden","autoreverses":false,"duration":1,"to":{"scalar":false}}],"fillMode":"both","autoreverses":false,"duration":1}],"layers":[],"texturedRectangle":{"isBackgroundTexture":true,"singleTextureOpacity":1,"textureType":5,"textBaseline":0,"textXHeight":0,"isVerticalText":false},"initialState":{"affineTransform":[1,0,0,1,0,0],"masksToBounds":false,"rotation":0,"scale":1,"position":{"pointX":148.9736328125,"pointY":77.09384155273438},"width":300,"sublayerTransform":[1,0,0,0,0,1,0,0,0,0,1,0,0,0,0,1],"contentsRect":{"y":0,"x":0,"width":1,"height":1},"opacity":1,"edgeAntialiasingMask":0,"height":158,"hidden":true,"anchorPoint":{"pointX":0.5,"pointY":0.5}},"texture":"72A2651E9F667A812EBAE78CE475F002"}]}]},"effects":[],"duration":1,"type":"buildIn","name":"apple:dissolve","objectID":"5F068AF4-49C1-41BD-9D0B-F351C387611E"}],"automaticPlay":false,"hyperlinks":[],"accessibility":[{"text":"feather.png","targetRectangle":{"y":235.0263671875,"x":427.6814575195312,"width":168.6371002197266,"height":297.947265625}},{"text":"SERVIDOR","targetRectangle":{"y":729.2687065601349,"x":908.6099982261658,"width":100.78,"height":24.41986083984375}},{"text":"2000px-Ardebian_logo.svg.png","targetRectangle":{"y":235.0263671875,"x":59.0263671875,"width":297.947265625,"height":297.947265625}}],"baseLayer":{"animations":[],"initialState":{"affineTransform":[1,0,0,1,0,0],"masksToBounds":false,"rotation":0,"scale":1,"position":{"pointX":512,"pointY":384},"width":1024,"sublayerTransform":[1,0,0,0,0,1,0,0,0,0,1,0,0,0,0,1],"contentsRect":{"y":0,"x":0,"width":1,"height":1},"opacity":1,"edgeAntialiasingMask":251658240,"height":768,"hidden":false,"anchorPoint":{"pointX":0.5,"pointY":0.5}},"layers":[{"animations":[],"initialState":{"affineTransform":[1,0,0,1,0,0],"masksToBounds":false,"rotation":0,"scale":1,"position":{"pointX":512,"pointY":384},"width":1024,"sublayerTransform":[1,0,0,0,0,1,0,0,0,0,1,0,0,0,0,1],"contentsRect":{"y":0,"x":0,"width":1,"height":1},"opacity":1,"edgeAntialiasingMask":251658240,"height":768,"hidden":false,"anchorPoint":{"pointX":0.5,"pointY":0.5}},"layers":[{"animations":[],"initialState":{"affineTransform":[1,0,0,1,0,0],"masksToBounds":false,"rotation":0,"scale":1,"position":{"pointX":512,"pointY":384},"width":1024,"sublayerTransform":[1,0,0,0,0,1,0,0,0,0,1,0,0,0,0,1],"contentsRect":{"y":0,"x":0,"width":1,"height":1},"opacity":1,"edgeAntialiasingMask":251658240,"height":768,"hidden":false,"anchorPoint":{"pointX":0.5,"pointY":0.5}},"layers":[{"animations":[],"layers":[],"texturedRectangle":{"isBackgroundTexture":true,"singleTextureOpacity":1,"textureType":1,"textBaseline":0,"textXHeight":0,"isVerticalText":false},"initialState":{"affineTransform":[1,0,0,1,0,0],"masksToBounds":false,"rotation":0,"scale":1,"position":{"pointX":512,"pointY":384},"width":1024,"sublayerTransform":[1,0,0,0,0,1,0,0,0,0,1,0,0,0,0,1],"contentsRect":{"y":0,"x":0,"width":1,"height":1},"opacity":1,"edgeAntialiasingMask":0,"height":768,"hidden":false,"anchorPoint":{"pointX":0.5,"pointY":0.5}},"texture":"DFDBC287DA3C930BF833C0D0D18B1670"}]}]},{"animations":[],"initialState":{"affineTransform":[1,0,0,1,0,0],"masksToBounds":false,"rotation":0,"scale":1,"position":{"pointX":512,"pointY":384},"width":1024,"sublayerTransform":[1,0,0,0,0,1,0,0,0,0,1,0,0,0,0,1],"contentsRect":{"y":0,"x":0,"width":1,"height":1},"opacity":1,"edgeAntialiasingMask":251658240,"height":768,"hidden":false,"anchorPoint":{"pointX":0.5,"pointY":0.5}},"layers":[{"animations":[],"initialState":{"affineTransform":[1,0,0,1,0,0],"masksToBounds":false,"rotation":0,"scale":1,"position":{"pointX":512,"pointY":4.771605014801025},"width":1024,"sublayerTransform":[1,0,0,0,0,1,0,0,0,0,1,0,0,0,0,1],"contentsRect":{"y":0,"x":0,"width":1,"height":1},"opacity":1,"edgeAntialiasingMask":251658240,"height":9.9453125,"hidden":false,"anchorPoint":{"pointX":0.5,"pointY":0.5}},"layers":[{"animations":[],"layers":[],"texturedRectangle":{"singleTextureOpacity":1,"textXHeight":0,"shapePath":{"lineWidth":1,"flatness":0.6,"lineCapStyle":0,"elements":[{"type":"MoveToPoint","points":[[1,1.798948764801025]]},{"type":"AddLine","points":[[1025,1.798948764801025]]},{"type":"AddLine","points":[[1025,11.74426126480103]]},{"type":"AddLine","points":[[1,11.74426126480103]]},{"type":"CloseSubpath"},{"type":"MoveToPoint","points":[[1,1.798948764801025]]}],"windingRule":0,"lineJoinStyle":0,"miterLimit":10},"isBackgroundTexture":true,"textBaseline":0,"isVerticalText":false,"textureType":5},"initialState":{"affineTransform":[1,0,0,1,0,0],"masksToBounds":false,"rotation":0,"scale":1,"position":{"pointX":512,"pointY":4.701051235198975},"width":1026,"sublayerTransform":[1,0,0,0,0,1,0,0,0,0,1,0,0,0,0,1],"contentsRect":{"y":0,"x":0,"width":1,"height":1},"opacity":1,"edgeAntialiasingMask":0,"height":13,"hidden":false,"anchorPoint":{"pointX":0.5,"pointY":0.5}},"texture":"4D228BDFA1F59F0125B92E3A19605505"}]}]},{"animations":[],"initialState":{"affineTransform":[1,0,0,1,0,0],"masksToBounds":false,"rotation":0,"scale":1,"position":{"pointX":512,"pointY":384},"width":1024,"sublayerTransform":[1,0,0,0,0,1,0,0,0,0,1,0,0,0,0,1],"contentsRect":{"y":0,"x":0,"width":1,"height":1},"opacity":1,"edgeAntialiasingMask":251658240,"height":768,"hidden":false,"anchorPoint":{"pointX":0.5,"pointY":0.5}},"layers":[{"animations":[],"initialState":{"affineTransform":[1,0,0,1,0,0],"masksToBounds":false,"rotation":0,"scale":1,"position":{"pointX":208,"pointY":384},"width":297.947265625,"sublayerTransform":[1,0,0,0,0,1,0,0,0,0,1,0,0,0,0,1],"contentsRect":{"y":0,"x":0,"width":1,"height":1},"opacity":1,"edgeAntialiasingMask":251658240,"height":297.947265625,"hidden":false,"anchorPoint":{"pointX":0.5,"pointY":0.5}},"objectID":"A8A4ABB2-10C0-44A2-8E79-2ED18D4FC8FC","layers":[{"animations":[],"layers":[],"texturedRectangle":{"isBackgroundTexture":true,"singleTextureOpacity":1,"textureType":5,"textBaseline":0,"textXHeight":0,"isVerticalText":false},"initialState":{"affineTransform":[1,0,0,1,0,0],"masksToBounds":false,"rotation":0,"scale":1,"position":{"pointX":148.9736328125,"pointY":148.9736328125},"width":300,"sublayerTransform":[1,0,0,0,0,1,0,0,0,0,1,0,0,0,0,1],"contentsRect":{"y":0,"x":0,"width":1,"height":1},"opacity":1,"edgeAntialiasingMask":0,"height":300,"hidden":false,"anchorPoint":{"pointX":0.5,"pointY":0.5}},"texture":"D7D7E4D8DB5C357981D01D15B5C6A61B"}]}]},{"animations":[],"initialState":{"affineTransform":[1,0,0,1,0,0],"masksToBounds":false,"rotation":0,"scale":1,"position":{"pointX":512,"pointY":384},"width":1024,"sublayerTransform":[1,0,0,0,0,1,0,0,0,0,1,0,0,0,0,1],"contentsRect":{"y":0,"x":0,"width":1,"height":1},"opacity":1,"edgeAntialiasingMask":251658240,"height":768,"hidden":false,"anchorPoint":{"pointX":0.5,"pointY":0.5}},"layers":[{"animations":[],"initialState":{"affineTransform":[1,0,0,1,0,0],"masksToBounds":false,"rotation":0,"scale":1,"position":{"pointX":512.0000076293945,"pointY":384},"width":168.6371002197266,"sublayerTransform":[1,0,0,0,0,1,0,0,0,0,1,0,0,0,0,1],"contentsRect":{"y":0,"x":0,"width":1,"height":1},"opacity":1,"edgeAntialiasingMask":251658240,"height":297.947265625,"hidden":false,"anchorPoint":{"pointX":0.5,"pointY":0.5}},"objectID":"499115BB-BDA5-48F8-98AC-F013E4FB8150","layers":[{"animations":[],"layers":[],"texturedRectangle":{"isBackgroundTexture":true,"singleTextureOpacity":1,"textureType":5,"textBaseline":0,"textXHeight":0,"isVerticalText":false},"initialState":{"affineTransform":[1,0,0,1,0,0],"masksToBounds":false,"rotation":0,"scale":1,"position":{"pointX":84.31854248046875,"pointY":148.9736328125},"width":172,"sublayerTransform":[1,0,0,0,0,1,0,0,0,0,1,0,0,0,0,1],"contentsRect":{"y":0,"x":0,"width":1,"height":1},"opacity":1,"edgeAntialiasingMask":0,"height":300,"hidden":false,"anchorPoint":{"pointX":0.5,"pointY":0.5}},"texture":"57F37F491EDE3BFBC2330D8CB150D3FD"}]}]},{"animations":[],"initialState":{"affineTransform":[1,0,0,1,0,0],"masksToBounds":false,"rotation":0,"scale":1,"position":{"pointX":512,"pointY":384},"width":1024,"sublayerTransform":[1,0,0,0,0,1,0,0,0,0,1,0,0,0,0,1],"contentsRect":{"y":0,"x":0,"width":1,"height":1},"opacity":1,"edgeAntialiasingMask":251658240,"height":768,"hidden":false,"anchorPoint":{"pointX":0.5,"pointY":0.5}},"layers":[{"animations":[],"initialState":{"affineTransform":[1,0,0,1,0,0],"masksToBounds":false,"rotation":0,"scale":1,"position":{"pointX":797,"pointY":384.0000152587891},"width":297.947265625,"sublayerTransform":[1,0,0,0,0,1,0,0,0,0,1,0,0,0,0,1],"contentsRect":{"y":0,"x":0,"width":1,"height":1},"opacity":1,"edgeAntialiasingMask":251658240,"height":154.1877136230469,"hidden":false,"anchorPoint":{"pointX":0.5,"pointY":0.5}},"objectID":"5F068AF4-49C1-41BD-9D0B-F351C387611E","layers":[{"animations":[],"layers":[],"texturedRectangle":{"isBackgroundTexture":true,"singleTextureOpacity":1,"textureType":5,"textBaseline":0,"textXHeight":0,"isVerticalText":false},"initialState":{"affineTransform":[1,0,0,1,0,0],"masksToBounds":false,"rotation":0,"scale":1,"position":{"pointX":148.9736328125,"pointY":77.09384155273438},"width":300,"sublayerTransform":[1,0,0,0,0,1,0,0,0,0,1,0,0,0,0,1],"contentsRect":{"y":0,"x":0,"width":1,"height":1},"opacity":1,"edgeAntialiasingMask":0,"height":158,"hidden":true,"anchorPoint":{"pointX":0.5,"pointY":0.5}},"texture":"72A2651E9F667A812EBAE78CE475F002"}]}]},{"animations":[],"initialState":{"affineTransform":[1,0,0,1,0,0],"masksToBounds":false,"rotation":0,"scale":1,"position":{"pointX":512,"pointY":384},"width":1024,"sublayerTransform":[1,0,0,0,0,1,0,0,0,0,1,0,0,0,0,1],"contentsRect":{"y":0,"x":0,"width":1,"height":1},"opacity":1,"edgeAntialiasingMask":251658240,"height":768,"hidden":false,"anchorPoint":{"pointX":0.5,"pointY":0.5}},"layers":[{"animations":[],"initialState":{"affineTransform":[1,0,0,1,0,0],"masksToBounds":false,"rotation":0,"scale":1,"position":{"pointX":874.1346811056137,"pointY":741.4786378622521},"width":40.90644717216492,"sublayerTransform":[1,0,0,0,0,1,0,0,0,0,1,0,0,0,0,1],"contentsRect":{"y":0,"x":0,"width":1,"height":1},"opacity":1,"edgeAntialiasingMask":251658240,"height":33.00000033387914,"hidden":false,"anchorPoint":{"pointX":0.5,"pointY":0.5}},"layers":[{"animations":[],"layers":[],"texturedRectangle":{"singleTextureOpacity":1,"textXHeight":0,"shapePath":{"lineWidth":1,"flatness":0.6,"lineCapStyle":0,"elements":[{"type":"MoveToPoint","points":[[2.563502786681056,1.9786376953125]]},{"type":"AddCurve","points":[[2.077943146394546,1.9786376953125],[1.681459079988372,2.375123351061688],[1.68145751953125,2.860683026723564]]},{"type":"AddLine","points":[[1.68145751953125,29.14307724963874]]},{"type":"AddCurve","points":[[1.68145751953125,29.62863536484338],[2.077946267308789,30.02512882287874],[2.563502786681056,30.0251225810498]]},{"type":"AddLine","points":[[18.58732513990253,30.0251225810498]]},{"type":"AddLine","points":[[18.52980044856668,30.27120044524781]]},{"type":"AddLine","points":[[17.84269996872172,33.70350727834739]]},{"type":"AddLine","points":[[15.83253158815205,33.70350727834739]]},{"type":"AddLine","points":[[15.83253158815205,34.97863802919164]]},{"type":"AddLine","points":[[21.12799900723621,34.97863802919164]]},{"type":"AddLine","points":[[22.30725517962128,34.97863802919164]]},{"type":"AddLine","points":[[27.60272259870544,34.97863802919164]]},{"type":"AddLine","points":[[27.60272259870544,33.70350727834739]]},{"type":"AddLine","points":[[25.59255421813577,33.70350727834739]]},{"type":"AddLine","points":[[24.90545373829082,30.27120044524781]]},{"type":"AddLine","points":[[24.85112486314029,30.0251225810498]]},{"type":"AddLine","points":[[41.70585942454636,30.0251225810498]]},{"type":"AddCurve","points":[[42.19141750437575,30.0251225810498],[42.58790469169617,29.62863224392891],[42.58790469169617,29.14307724963874]]},{"type":"AddLine","points":[[42.58790469169617,2.860683026723564]]},{"type":"AddCurve","points":[[42.5876987113561,2.375123351061688],[42.19142374620424,1.9786376953125],[41.70585942454636,1.9786376953125]]},{"type":"AddLine","points":[[2.563502786681056,1.9786376953125]]},{"type":"CloseSubpath"},{"type":"MoveToPoint","points":[[22.13468110561371,2.793570881942287]]},{"type":"AddCurve","points":[[22.35138178610987,2.793570881942287],[22.52776649640873,2.969957165548863],[22.52776649640873,3.186656301375479]]},{"type":"AddCurve","points":[[22.52776649640873,3.403358558116565],[22.35137554428138,3.576542783476043],[22.13468110561371,3.576545904390514]]},{"type":"AddCurve","points":[[21.91798042511755,3.576545904390514],[21.74159571481869,3.403360118573801],[21.74159571481869,3.186656301375479]]},{"type":"AddCurve","points":[[21.74159571481869,2.969954044634392],[21.91798666694604,2.793569321485052],[22.13468110561371,2.793570881942287]]},{"type":"CloseSubpath"},{"type":"MoveToPoint","points":[[4.033578231930733,4.624773689545691]]},{"type":"AddLine","points":[[40.23578397929668,4.624773689545691]]},{"type":"AddLine","points":[[40.23578397929668,25.24418121948838]]},{"type":"AddLine","points":[[4.033578231930733,25.24418121948838]]},{"type":"AddLine","points":[[4.033578231930733,4.624773689545691]]},{"type":"CloseSubpath"},{"type":"MoveToPoint","points":[[4.033578231930733,4.624773689545691]]}],"windingRule":0,"lineJoinStyle":0,"miterLimit":10},"isBackgroundTexture":true,"textBaseline":0,"isVerticalText":false,"textureType":5},"initialState":{"affineTransform":[1,0,0,1,0,0],"masksToBounds":false,"rotation":0,"scale":1,"position":{"pointX":20.31854248046875,"pointY":16.0213623046875},"width":44,"sublayerTransform":[1,0,0,0,0,1,0,0,0,0,1,0,0,0,0,1],"contentsRect":{"y":0,"x":0,"width":1,"height":1},"opacity":1,"edgeAntialiasingMask":0,"height":36,"hidden":false,"anchorPoint":{"pointX":0.5,"pointY":0.5}},"texture":"EF1056C4F088B7A9DBDF5AA7AB176A86"}]}]},{"animations":[],"initialState":{"affineTransform":[1,0,0,1,0,0],"masksToBounds":false,"rotation":0,"scale":1,"position":{"pointX":512,"pointY":384},"width":1024,"sublayerTransform":[1,0,0,0,0,1,0,0,0,0,1,0,0,0,0,1],"contentsRect":{"y":0,"x":0,"width":1,"height":1},"opacity":1,"edgeAntialiasingMask":251658240,"height":768,"hidden":false,"anchorPoint":{"pointX":0.5,"pointY":0.5}},"layers":[{"animations":[],"initialState":{"affineTransform":[1,0,0,1,0,0],"masksToBounds":false,"rotation":0,"scale":1,"position":{"pointX":959,"pointY":741.4786376953125},"width":107.7800035476685,"sublayerTransform":[1,0,0,0,0,1,0,0,0,0,1,0,0,0,0,1],"contentsRect":{"y":0,"x":0,"width":1,"height":1},"opacity":1,"edgeAntialiasingMask":251658240,"height":30.41986227035522,"hidden":false,"anchorPoint":{"pointX":0.5,"pointY":0.5}},"layers":[{"animations":[],"layers":[],"texturedRectangle":{"singleTextureOpacity":1,"textXHeight":0.5442105263157895,"textBaseline":0.8604559270959151,"isBackgroundTexture":true,"isVerticalText":false,"textColor":[0,0,0,0.5],"textureType":6},"initialState":{"affineTransform":[1,0,0,1,0,0],"masksToBounds":false,"rotation":0,"scale":1,"position":{"pointX":54.39000177383423,"pointY":16.23129343986511},"width":103,"sublayerTransform":[1,0,0,0,0,1,0,0,0,0,1,0,0,0,0,1],"contentsRect":{"y":0,"x":0,"width":1,"height":1},"opacity":1,"edgeAntialiasingMask":0,"height":19,"hidden":false,"anchorPoint":{"pointX":0.5,"pointY":0.5}},"texture":"BB5FBA3B6F10FBEC956A14E318AB3F6E"}]}]}]}},{"effects":[{"beginTime":0,"baseLayer":{"animations":[],"initialState":{"affineTransform":[1,0,0,1,0,0],"masksToBounds":false,"rotation":0,"scale":1,"position":{"pointX":512,"pointY":384},"width":1024,"sublayerTransform":[1,0,0,0,0,1,0,0,0,0,1,0,0,0,0,1],"contentsRect":{"y":0,"x":0,"width":1,"height":1},"opacity":1,"edgeAntialiasingMask":251658240,"height":768,"hidden":false,"anchorPoint":{"pointX":0.5,"pointY":0.5}},"objectID":"0","layers":[{"animations":[],"initialState":{"affineTransform":[1,0,0,1,0,0],"masksToBounds":false,"rotation":0,"scale":1,"position":{"pointX":512,"pointY":384},"width":1024,"sublayerTransform":[1,0,0,0,0,1,0,0,0,0,1,-0.0004922987690640373,0,0,0,1],"contentsRect":{"y":0,"x":0,"width":1,"height":1},"opacity":1,"edgeAntialiasingMask":251658240,"height":768,"hidden":false,"anchorPoint":{"pointX":0.5,"pointY":0.5}},"layers":[{"animations":[],"layers":[],"texturedRectangle":{"isBackgroundTexture":false,"singleTextureOpacity":1,"textureType":0,"textBaseline":0,"textXHeight":0,"isVerticalText":false},"initialState":{"affineTransform":[1,0,0,1,0,0],"masksToBounds":false,"rotation":0,"scale":1,"position":{"pointX":512,"pointY":384},"width":1024,"sublayerTransform":[1,0,0,0,0,1,0,0,0,0,1,0,0,0,0,1],"contentsRect":{"y":0,"x":0,"width":1,"height":1},"opacity":1,"edgeAntialiasingMask":0,"height":768,"hidden":false,"anchorPoint":{"pointX":0.5,"pointY":0.5}},"texture":"0BD29801AF197E3A57AEDDF3FABD5E69"},{"animations":[{"timeOffset":0,"from":{"scalar":1},"beginTime":0,"repeatCount":0,"fillMode":"both","duration":1.5,"autoreverses":false,"timingFunction":"EaseInEaseOut","property":"opacity","to":{"scalar":0}}],"layers":[],"texturedRectangle":{"isBackgroundTexture":false,"singleTextureOpacity":1,"textureType":0,"textBaseline":0,"textXHeight":0,"isVerticalText":false},"initialState":{"affineTransform":[1,0,0,1,0,0],"masksToBounds":false,"rotation":0,"scale":1,"position":{"pointX":512,"pointY":384},"width":1024,"sublayerTransform":[1,0,0,0,0,1,0,0,0,0,1,0,0,0,0,1],"contentsRect":{"y":0,"x":0,"width":1,"height":1},"opacity":1,"edgeAntialiasingMask":0,"height":768,"hidden":false,"anchorPoint":{"pointX":0.5,"pointY":0.5}},"texture":"336208773D27FF0B1EEE8862274EFBD8"}]}]},"effects":[],"duration":1.5,"type":"transition","name":"apple:dissolve","objectID":"0"}],"automaticPlay":false,"hyperlinks":[],"accessibility":[{"text":"feather.png","targetRectangle":{"y":235.0263671875,"x":427.6814575195312,"width":168.6371002197266,"height":297.947265625}},{"text":"MySQL.png","targetRectangle":{"y":306.9061584472656,"x":648.0263671875,"width":297.947265625,"height":154.1877136230469}},{"text":"SERVIDOR","targetRectangle":{"y":729.2687065601349,"x":908.6099982261658,"width":100.78,"height":24.41986083984375}},{"text":"2000px-Ardebian_logo.svg.png","targetRectangle":{"y":235.0263671875,"x":59.0263671875,"width":297.947265625,"height":297.947265625}}],"baseLayer":{"animations":[],"initialState":{"affineTransform":[1,0,0,1,0,0],"masksToBounds":false,"rotation":0,"scale":1,"position":{"pointX":512,"pointY":384},"width":1024,"sublayerTransform":[1,0,0,0,0,1,0,0,0,0,1,0,0,0,0,1],"contentsRect":{"y":0,"x":0,"width":1,"height":1},"opacity":1,"edgeAntialiasingMask":251658240,"height":768,"hidden":false,"anchorPoint":{"pointX":0.5,"pointY":0.5}},"objectID":"0","layers":[{"animations":[],"initialState":{"affineTransform":[1,0,0,1,0,0],"masksToBounds":false,"rotation":0,"scale":1,"position":{"pointX":512,"pointY":384},"width":1024,"sublayerTransform":[1,0,0,0,0,1,0,0,0,0,1,-0.0004922987690640373,0,0,0,1],"contentsRect":{"y":0,"x":0,"width":1,"height":1},"opacity":1,"edgeAntialiasingMask":251658240,"height":768,"hidden":false,"anchorPoint":{"pointX":0.5,"pointY":0.5}},"layers":[{"animations":[],"layers":[],"texturedRectangle":{"isBackgroundTexture":false,"singleTextureOpacity":1,"textureType":0,"textBaseline":0,"textXHeight":0,"isVerticalText":false},"initialState":{"affineTransform":[1,0,0,1,0,0],"masksToBounds":false,"rotation":0,"scale":1,"position":{"pointX":512,"pointY":384},"width":1024,"sublayerTransform":[1,0,0,0,0,1,0,0,0,0,1,0,0,0,0,1],"contentsRect":{"y":0,"x":0,"width":1,"height":1},"opacity":1,"edgeAntialiasingMask":0,"height":768,"hidden":false,"anchorPoint":{"pointX":0.5,"pointY":0.5}},"texture":"336208773D27FF0B1EEE8862274EFBD8"}]}]}}]}